harvey/__init__.py
harvey/api.py
harvey/app.py
harvey/config.py
harvey/containers.py
harvey/deployments.py
harvey/errors.py
harvey/git.py
harvey/locks.py
harvey/messages.py
harvey/py.typed
harvey/webhooks.py
harvey/repos/__init__.py
harvey/repos/deployments.py
harvey/repos/locks.py
harvey/repos/projects.py
harvey/repos/webhooks.py
harvey/utils/__init__.py
harvey/utils/api_utils.py
harvey/utils/deployments.py
harvey/utils/utils.py
harvey_cd-0.24.0.dist-info/LICENSE
harvey_cd-0.24.0.dist-info/METADATA
harvey_cd-0.24.0.dist-info/WHEEL
harvey_cd-0.24.0.dist-info/entry_points.txt
harvey_cd-0.24.0.dist-info/top_level.txt
harvey_cd-0.24.0.dist-info/RECORD
