Metadata-Version: 2.1
Name: harvey-cd
Version: 0.24.0
Summary: The lightweight Docker Compose deployment platform.
Home-page: http://github.com/justintime50/harvey
Author: Justintime50
License: MIT
Classifier: Programming Language :: Python :: 3
Classifier: License :: OSI Approved :: MIT License
Classifier: Operating System :: OS Independent
Requires-Python: >=3.7, <4
License-File: LICENSE
Requires-Dist: docker (==6.1.*)
Requires-Dist: flask (==2.*)
Requires-Dist: python-dotenv (==0.21.*)
Requires-Dist: pyyaml (==6.*)
Requires-Dist: requests (==2.*)
Requires-Dist: requests-unixsocket (==0.3.*)
Requires-Dist: sentry-sdk (==1.*)
Requires-Dist: slackclient (==2.*)
Requires-Dist: sqlitedict (==2.1.*)
Requires-Dist: uwsgi (==2.0.21)
Requires-Dist: woodchips (==0.2.*)
Provides-Extra: dev
Requires-Dist: bandit (==1.7.*) ; extra == 'dev'
Requires-Dist: black (==23.*) ; extra == 'dev'
Requires-Dist: build (==0.10.*) ; extra == 'dev'
Requires-Dist: flake8 (==5.*) ; extra == 'dev'
Requires-Dist: isort (==5.*) ; extra == 'dev'
Requires-Dist: mypy (==1.1.*) ; extra == 'dev'
Requires-Dist: pytest (==7.*) ; extra == 'dev'
Requires-Dist: pytest-cov (==4.*) ; extra == 'dev'
Requires-Dist: twine (==4.*) ; extra == 'dev'
Requires-Dist: types-PyYAML ; extra == 'dev'
Requires-Dist: types-requests ; extra == 'dev'
Requires-Dist: wheel (==0.40.*) ; extra == 'dev'
